catchbot/__init__.py
catchbot/celery_app.py
catchbot/config.py
catchbot/router_bot.py
catchbot/routes.py
catchbot/tasks.py
catchbot/updater.py
catchbot/commands/__init__.py
catchbot/commands/start.py
catchbot/hook/__init__.py
catchbot/hook/tree.py
catchbot/message/__init__.py
catchbot/message/header_parser.py
catchbot/message/message.py
catchbot/message/content/__init__.py
catchbot/message/content/dynamic.py
catchbot/message/content/loaders.py
catchbot/message/content/static.py
catchbot-0.7.0.dist-info/DESCRIPTION.rst
catchbot-0.7.0.dist-info/METADATA
catchbot-0.7.0.dist-info/RECORD
catchbot-0.7.0.dist-info/WHEEL
catchbot-0.7.0.dist-info/metadata.json
catchbot-0.7.0.dist-info/top_level.txt
